Metadata-Version: 1.0
Name: distributions-lp
Version: 0.2
Summary: Gaussian distributions
Home-page: UNKNOWN
Author: itz_me_LP
Author-email: UNKNOWN
License: UNKNOWN
Platform: UNKNOWN
